bootstrap.py
buildout.cfg
setup.py
sx/__init__.py
sx.translations.egg-info/PKG-INFO
sx.translations.egg-info/SOURCES.txt
sx.translations.egg-info/dependency_links.txt
sx.translations.egg-info/not-zip-safe
sx.translations.egg-info/requires.txt
sx.translations.egg-info/top_level.txt
sx/translations/__init__.py
sx/translations/license.txt
sx/translations/meta.zcml
sx/translations/readme.txt
sx/translations/version.txt
sx/translations/zcml.py
sx/translations/tests/__init__.py
sx/translations/tests/spanner.pot
sx/translations/tests/test_interfaces.py
sx/translations/tests/test_zcml.py