Metadata-Version: 1.0
Name: sx.translations
Version: 1.1
Summary: An enhanced version of zope.i18n.translationdomain
Home-page: http://www.simplistix.co.uk/software/zope/sx.translations
Author: Chris Withers
Author-email: chris@simplistix.co.uk
License: MIT
Platform: UNKNOWN
